rows2prose/__init__.py
rows2prose/notebook.py
rows2prose/web.py
rows2prose/package_data/.DS_Store
rows2prose/package_data/d3.min.js
rows2prose/package_data/rows2prose.browser.js
rows2prose/package_data/rows2prose.browser.js.map
rows2prose-0.1.0.dist-info/LICENSE
rows2prose-0.1.0.dist-info/METADATA
rows2prose-0.1.0.dist-info/WHEEL
rows2prose-0.1.0.dist-info/top_level.txt
rows2prose-0.1.0.dist-info/RECORD
